<?xml version='1.0' encoding='utf-8' ?>
<!DOCTYPE appendix PUBLIC "-//OASIS//DTD DocBook XML V4.5//EN" "http://www.oasis-open.org/docbook/xml/4.5/docbookx.dtd" [
<!ENTITY % BOOK_ENTITIES SYSTEM "AAR_Template.ent">
%BOOK_ENTITIES;
]>
<appendix id="appe-AAR_Template-Revision_History">
  <title>Revision History</title>
  <simpara>
    <revhistory>
      <revision>
	<revnumber>0.2</revnumber>
	<date>Sat Nov 26 2011</date>
	<author>
	  <firstname>John</firstname>
	  <surname>McDonough</surname>
	  <email>wb8rcr@arrl.net</email>
	</author>
	<revdescription>
	  <simplelist>
	    <member>Add index entries</member>
	    <member>Add list of contributors</member>
	  </simplelist>
	</revdescription>
      </revision>
      <revision>
	<revnumber>0.1</revnumber>
	<date>Tue Nov 15 2011</date>
	<author>
	  <firstname>John</firstname>
	  <surname>McDonough</surname>
	  <email>wb8rcr@arrl.net</email>
	</author>
	<revdescription>
	  <simplelist>
	    <member>Initial draft</member>
	  </simplelist>
	</revdescription>
      </revision>
      <revision>
	<revnumber>0.0</revnumber>
	<date>Thu Oct 27 2011</date>
	<author>
	  <firstname>John</firstname>
	  <surname>McDonough</surname>
	  <email>wb8rcr@arrl.net</email>
	</author>
	<revdescription>
	  <simplelist>
	    <member>Initial template instantiation</member>
	  </simplelist>
	</revdescription>
      </revision>
    </revhistory>
  </simpara>
</appendix>

